<?xml version="1.0" encoding="UTF-8" ?>
<!DOCTYPE mapper PUBLIC "-//mybatis.org//DTD Mapper 3.0//EN" "http://mybatis.org/dtd/mybatis-3-mapper.dtd" >
<mapper namespace="com.mouchina.moumou_server.dao.member.BusinessMapper">
	<resultMap id="BaseResultMap"
		type="com.mouchina.moumou_server.entity.member.Business">
		<!-- WARNING - @mbggenerated This element is automatically generated by 
			MyBatis Generator, do not modify. This element was generated on Mon Feb 01 
			16:24:57 CST 2016. -->
		<id column="id" property="id" jdbcType="BIGINT" />
		<result column="user_id" property="userId" jdbcType="BIGINT" />
		<result column="business_name" property="businessName"
			jdbcType="VARCHAR" />
		<result column="business_address" property="businessAddress"
			jdbcType="VARCHAR" />
		<result column="business_tel" property="businessTel" jdbcType="VARCHAR" />
		<result column="business_site" property="businessSite"
			jdbcType="VARCHAR" />
		<result column="business_qq" property="businessQq" jdbcType="VARCHAR" />
		<result column="business_weixin" property="businessWeixin"
			jdbcType="VARCHAR" />
		<result column="business_weibo" property="businessWeibo"
			jdbcType="VARCHAR" />
		<result column="business_credentials_up" property="businessCredentialsUp"
			jdbcType="VARCHAR" />
		<result column="business_credentials_down" property="businessCredentialsDown"
			jdbcType="VARCHAR" />
		<result column="business_credentials_face" property="businessCredentialsFace"
			jdbcType="VARCHAR" />
		<result column="create_time" property="createTime" jdbcType="TIMESTAMP" />
		<result column="modfiy_time" property="modfiyTime" jdbcType="TIMESTAMP" />
		<result column="state" property="state" jdbcType="TINYINT" />
		<result column="descb" property="descb" jdbcType="VARCHAR" />
		<result column="business_industry" property="businessIndustry"
			jdbcType="VARCHAR" />
		<result column="business_logo" property="businessLogo"
			jdbcType="VARCHAR" />
		<result column="detail_address" property="detailAddress"
			jdbcType="VARCHAR" />
		<result column="business_abbreviation" property="businessAbbreviation"
			jdbcType="VARCHAR" />
		<result column="registration_number" property="registrationNumber"
			jdbcType="VARCHAR" />
		<result column="apply_name" property="applyName" jdbcType="VARCHAR" />
		<result column="identity_card" property="identityCard"
			jdbcType="VARCHAR" />
		<result column="certification_type" property="certificationType"
			jdbcType="INTEGER" />
		<result column="phone" property="phone" jdbcType="CHAR" />
		<result column="province" property="province" jdbcType="VARCHAR" />
		<result column="city" property="city" jdbcType="VARCHAR" />
		<result column="area" property="area" jdbcType="VARCHAR" />
		<result column="avatar" property="avatar" jdbcType="VARCHAR" />
		

	</resultMap>
	<sql id="Base_Column_List">
		<!-- WARNING - @mbggenerated This element is automatically generated by 
			MyBatis Generator, do not modify. This element was generated on Mon Feb 01 
			16:24:57 CST 2016. -->
		id, user_id, business_name, business_address, business_tel,
		business_site, business_qq,
		business_weixin, business_weibo,
		business_credentials_up, business_credentials_down,
		business_credentials_face, create_time, modfiy_time,
		state,descb,business_industry,business_logo,detail_address,
		business_abbreviation,registration_number,apply_name,identity_card,certification_type,province,
		city,area,business_full_name,business_license_num,coordinate,phone,province,city,area
	</sql>
	<select id="selectByPrimaryKey" resultMap="BaseResultMap"
		parameterType="java.lang.Long">
		<!-- WARNING - @mbggenerated This element is automatically generated by 
			MyBatis Generator, do not modify. This element was generated on Mon Feb 01 
			16:24:57 CST 2016. -->
		select
		<include refid="Base_Column_List" />
		from business
		where id = #{id,jdbcType=BIGINT}
	</select>
	<delete id="deleteByPrimaryKey" parameterType="java.lang.Long">
		<!-- WARNING - @mbggenerated This element is automatically generated by 
			MyBatis Generator, do not modify. This element was generated on Mon Feb 01 
			16:24:57 CST 2016. -->
		delete from business
		where id = #{id,jdbcType=BIGINT}
	</delete>
	<insert id="insert" parameterType="com.mouchina.moumou_server.entity.member.Business">
		<!-- WARNING - @mbggenerated This element is automatically generated by 
			MyBatis Generator, do not modify. This element was generated on Mon Feb 01 
			16:24:57 CST 2016. -->
		insert into business (id, user_id, business_name,
		business_address,
		business_tel, business_site,
		business_qq, business_weixin,
		business_weibo,
		business_credentials_up, business_credentials_down,
		business_credentials_face, create_time,
		modfiy_time, state)
		values
		(#{id,jdbcType=BIGINT}, #{userId,jdbcType=BIGINT},
		#{businessName,jdbcType=VARCHAR},
		#{businessAddress,jdbcType=VARCHAR},
		#{businessTel,jdbcType=VARCHAR}, #{businessSite,jdbcType=VARCHAR},
		#{businessQq,jdbcType=VARCHAR}, #{businessWeixin,jdbcType=VARCHAR},
		#{businessWeibo,jdbcType=VARCHAR},
		#{businessCredentialsUp,jdbcType=VARCHAR},
		#{businessCredentialsDown,jdbcType=VARCHAR},
		#{businessCredentialsFace,jdbcType=VARCHAR},
		#{createTime,jdbcType=TIMESTAMP},
		#{modfiyTime,jdbcType=TIMESTAMP},
		#{state,jdbcType=TINYINT})
	</insert>
	<insert id="insertSelective" parameterType="com.mouchina.moumou_server.entity.member.Business"
		useGeneratedKeys="true" keyProperty="id">
		<!-- WARNING - @mbggenerated This element is automatically generated by 
			MyBatis Generator, do not modify. This element was generated on Mon Feb 01 
			16:24:57 CST 2016. -->
		insert into business
		<trim prefix="(" suffix=")" suffixOverrides=",">
			<!-- <if test="id != null" > id, </if> -->
			<if test="userId != null">
				user_id,
			</if>
			<if test="businessName != null">
				business_name,
			</if>
			<if test="businessAddress != null">
				business_address,
			</if>
			<if test="businessTel != null">
				business_tel,
			</if>
			<if test="businessSite != null">
				business_site,
			</if>
			<if test="businessQq != null">
				business_qq,
			</if>
			<if test="businessWeixin != null">
				business_weixin,
			</if>
			<if test="businessWeibo != null">
				business_weibo,
			</if>
			<if test="businessCredentialsUp != null">
				business_credentials_up,
			</if>
			<if test="businessCredentialsDown != null">
				business_credentials_down,
			</if>
			<if test="businessCredentialsFace != null">
				business_credentials_face,
			</if>
			<if test="createTime != null">
				create_time,
			</if>
			<if test="modfiyTime != null">
				modfiy_time,
			</if>
			<if test="state != null">
				state,
			</if>
			<if test="descb != null">
				descb,
			</if>
			<if test="businessIndustry != null">
				business_industry,
			</if>
			<if test="businessLogo != null">
				business_logo,
			</if>
			<if test="detailAddress != null">
				detail_address,
			</if>
			<if test="businessAbbreviation != null">
				business_abbreviation,
			</if>
			<if test="registrationNumber != null">
				registration_number,
			</if>
			<if test="applyName != null">
				apply_name,
			</if>
			<if test="identityCard != null">
				identity_card,
			</if>
			<if test="certificationType != null">
				certification_type,
			</if>
			<if test="province != null">
				province,
			</if>
			<if test="city != null">
				city,
			</if>
			<if test="area != null">
				area,
			</if>
			<if test="businessFullName != null">
				business_full_name,
			</if>
			<if test="businessLicenseNum != null">
				business_license_num,
			</if>
			<if test="phone != null">
				phone,
			</if>
		</trim>
		<trim prefix="values (" suffix=")" suffixOverrides=",">
			<!-- <if test="id != null" > #{id,jdbcType=BIGINT}, </if> -->
			<if test="userId != null">
				#{userId,jdbcType=BIGINT},
			</if>
			<if test="businessName != null">
				#{businessName,jdbcType=VARCHAR},
			</if>
			<if test="businessAddress != null">
				#{businessAddress,jdbcType=VARCHAR},
			</if>
			<if test="businessTel != null">
				#{businessTel,jdbcType=VARCHAR},
			</if>
			<if test="businessSite != null">
				#{businessSite,jdbcType=VARCHAR},
			</if>
			<if test="businessQq != null">
				#{businessQq,jdbcType=VARCHAR},
			</if>
			<if test="businessWeixin != null">
				#{businessWeixin,jdbcType=VARCHAR},
			</if>
			<if test="businessWeibo != null">
				#{businessWeibo,jdbcType=VARCHAR},
			</if>
			<if test="businessCredentialsUp != null">
				#{businessCredentialsUp,jdbcType=VARCHAR},
			</if>
			<if test="businessCredentialsDown != null">
				#{businessCredentialsDown,jdbcType=VARCHAR},
			</if>
			<if test="businessCredentialsFace != null">
				#{businessCredentialsFace,jdbcType=VARCHAR},
			</if>
			<if test="createTime != null">
				#{createTime,jdbcType=TIMESTAMP},
			</if>
			<if test="modfiyTime != null">
				#{modfiyTime,jdbcType=TIMESTAMP},
			</if>
			<if test="state != null">
				#{state,jdbcType=TINYINT},
			</if>
			<if test="descb != null">
				#{descb,jdbcType=VARCHAR},
			</if>
			<if test="businessIndustry != null">
				#{businessIndustry,jdbcType=VARCHAR},
			</if>
			<if test="businessLogo != null">
				#{businessLogo,jdbcType=VARCHAR},
			</if>
			<if test="detailAddress != null">
				#{detailAddress,jdbcType=VARCHAR},
			</if>
			<if test="businessAbbreviation != null">
				#{businessAbbreviation,jdbcType=VARCHAR},
			</if>
			<if test="registrationNumber != null">
				#{registrationNumber,jdbcType=VARCHAR},
			</if>
			<if test="applyName != null">
				#{applyName,jdbcType=VARCHAR},
			</if>
			<if test="identityCard != null">
				#{identityCard,jdbcType=VARCHAR},
			</if>
			<if test="certificationType != null">
				#{certificationType,jdbcType=INTEGER},
			</if>
			<if test="province != null">
				#{province,jdbcType=VARCHAR},
			</if>
			<if test="city != null">
				#{city,jdbcType=VARCHAR},
			</if>
			<if test="area != null">
				#{area,jdbcType=VARCHAR},
			</if>
			<if test="businessFullName != null">
				#{businessFullName,jdbcType=VARCHAR},
			</if>
			<if test="businessLicenseNum != null">
				#{businessLicenseNum,jdbcType=VARCHAR},
			</if>
			<if test="phone != null">
				#{phone,jdbcType=CHAR},
			</if>
		</trim>
	</insert>

	<update id="updateByPrimaryKeySelective" parameterType="com.mouchina.moumou_server.entity.member.Business">
		<!-- WARNING - @mbggenerated This element is automatically generated by 
			MyBatis Generator, do not modify. This element was generated on Mon Feb 01 
			16:24:57 CST 2016. -->
		update business
		<set>
			<if test="userId != null">
				user_id = #{userId,jdbcType=BIGINT},
			</if>
			<if test="businessName != null">
				business_name = #{businessName,jdbcType=VARCHAR},
			</if>
			<if test="businessAddress != null">
				business_address = #{businessAddress,jdbcType=VARCHAR},
			</if>
			<if test="businessTel != null">
				business_tel = #{businessTel,jdbcType=VARCHAR},
			</if>
			<if test="businessSite != null">
				business_site = #{businessSite,jdbcType=VARCHAR},
			</if>
			<if test="businessQq != null">
				business_qq = #{businessQq,jdbcType=VARCHAR},
			</if>
			<if test="businessWeixin != null">
				business_weixin = #{businessWeixin,jdbcType=VARCHAR},
			</if>
			<if test="businessWeibo != null">
				business_weibo = #{businessWeibo,jdbcType=VARCHAR},
			</if>
			<if test="businessCredentialsUp != null">
				business_credentials_up =
				#{businessCredentialsUp,jdbcType=VARCHAR},
			</if>
			<if test="businessCredentialsDown != null">
				business_credentials_down =
				#{businessCredentialsDown,jdbcType=VARCHAR},
			</if>
			<if test="businessCredentialsFace != null">
				business_credentials_face =
				#{businessCredentialsFace,jdbcType=VARCHAR},
			</if>
			<if test="createTime != null">
				create_time = #{createTime,jdbcType=TIMESTAMP},
			</if>
			<if test="modfiyTime != null">
				modfiy_time = #{modfiyTime,jdbcType=TIMESTAMP},
			</if>
			<if test="state != null">
				state = #{state,jdbcType=TINYINT},
			</if>
			<if test="descb != null">
				descb= #{descb,jdbcType=VARCHAR},
			</if>
			<if test="businessIndustry != null">
				business_industry= #{businessIndustry,jdbcType=VARCHAR},
			</if>
			<if test="businessLogo != null">
				business_logo= #{businessLogo,jdbcType=VARCHAR},
			</if>
			<if test="detailAddress != null">
				detail_address= #{detailAddress,jdbcType=VARCHAR},
			</if>
			<if test="businessAbbreviation != null">
				business_abbreviation=
				#{businessAbbreviation,jdbcType=VARCHAR},
			</if>
			<if test="registrationNumber != null">
				registration_number=
				#{registrationNumber,jdbcType=VARCHAR},
			</if>
			<if test="applyName != null">
				apply_name= #{applyName,jdbcType=VARCHAR},
			</if>
			<if test="identityCard != null">
				identity_card= #{identityCard,jdbcType=VARCHAR},
			</if>
			<if test="certificationType != null">
				certification_type=
				#{certificationType,jdbcType=INTEGER},
			</if>
		</set>
		where id = #{id,jdbcType=BIGINT}
	</update>
	<update id="updateByPrimaryKey" parameterType="com.mouchina.moumou_server.entity.member.Business">
		<!-- WARNING - @mbggenerated This element is automatically generated by 
			MyBatis Generator, do not modify. This element was generated on Mon Feb 01 
			16:24:57 CST 2016. -->
		update business
		set user_id = #{userId,jdbcType=BIGINT},
		business_name =
		#{businessName,jdbcType=VARCHAR},
		business_address =
		#{businessAddress,jdbcType=VARCHAR},
		business_tel =
		#{businessTel,jdbcType=VARCHAR},
		business_site =
		#{businessSite,jdbcType=VARCHAR},
		business_qq =
		#{businessQq,jdbcType=VARCHAR},
		business_weixin =
		#{businessWeixin,jdbcType=VARCHAR},
		business_weibo =
		#{businessWeibo,jdbcType=VARCHAR},
		business_credentials_up =
		#{businessCredentialsUp,jdbcType=VARCHAR},
		business_credentials_down =
		#{businessCredentialsDown,jdbcType=VARCHAR},
		business_credentials_face
		=
		#{businessCredentialsFace,jdbcType=VARCHAR},
		create_time =
		#{createTime,jdbcType=TIMESTAMP},
		modfiy_time =
		#{modfiyTime,jdbcType=TIMESTAMP},
		state = #{state,jdbcType=TINYINT}
		where id = #{id,jdbcType=BIGINT}
	</update>
	<select id="selectModel" resultMap="BaseResultMap"
		parameterType="java.util.Map">
		select
		<include refid="Base_Column_List" />
		from
		moumou.business
		<where>
			<if test="id != null">
				and id= #{id,jdbcType=BIGINT}
			</if>
			<if test="userId != null">
				and user_id= #{userId,jdbcType=BIGINT}
			</if>
			<if test="businessName != null">
				and business_name= #{businessName,jdbcType=VARCHAR}
			</if>
			<if test="businessAddress != null">
				and business_address= #{businessAddress,jdbcType=VARCHAR}
			</if>
			<if test="businessTel != null">
				and business_tel= #{businessTel,jdbcType=VARCHAR}
			</if>
			<if test="businessSite != null">
				and business_site= #{businessSite,jdbcType=VARCHAR}
			</if>
			<if test="businessQq != null">
				and business_qq= #{businessQq,jdbcType=VARCHAR}
			</if>
			<if test="businessWeixin != null">
				and business_weixin= #{businessWeixin,jdbcType=VARCHAR}
			</if>
			<if test="businessWeibo != null">
				and business_weibo= #{businessWeibo,jdbcType=VARCHAR}
			</if>
			<if test="businessCredentialsUp != null">
				and business_credentials_up=
				#{businessCredentialsUp,jdbcType=VARCHAR}
			</if>
			<if test="businessCredentialsDown != null">
				and business_credentials_down=
				#{businessCredentialsDown,jdbcType=VARCHAR}
			</if>
			<if test="businessCredentialsFace != null">
				and business_credentials_face=
				#{businessCredentialsFace,jdbcType=VARCHAR}
			</if>
			<if test="createTime != null">
				and create_time= #{createTime,jdbcType=TIMESTAMP}
			</if>
			<if test="modfiyTime != null">
				and modfiy_time= #{modfiyTime,jdbcType=TIMESTAMP}
			</if>
			<if test="state != null">
				and state= #{state,jdbcType=TINYINT}
			</if>
			<if test="descb != null">
				and descb= #{descb,jdbcType=VARCHAR}
			</if>
			<if test="businessIndustry != null">
				and business_industry=
				#{businessIndustry,jdbcType=VARCHAR}
			</if>
			<if test="businessLogo != null">
				and business_logo= #{businessLogo,jdbcType=VARCHAR}
			</if>
			<if test="detailAddress != null">
				and detail_address= #{detailAddress,jdbcType=VARCHAR}
			</if>
			<if test="businessAbbreviation != null">
				and business_abbreviation=
				#{businessAbbreviation,jdbcType=VARCHAR},
			</if>
			<if test="registrationNumber != null">
				and registration_number=
				#{registrationNumber,jdbcType=VARCHAR},
			</if>
			<if test="applyName != null">
				and apply_name= #{applyName,jdbcType=VARCHAR},
			</if>
			<if test="identityCard != null">
				and identity_card= #{identityCard,jdbcType=VARCHAR},
			</if>
			<if test="certificationType != null">
				and certification_type=
				#{certificationType,jdbcType=INTEGER},
			</if>
		</where>
		<if test="order != null">
      <![CDATA[  order by  ${order} ]]>
		</if>
	</select>
	<select id="selectList" resultMap="BaseResultMap" parameterType="java.util.Map">
		select
		<include refid="Base_Column_List" />
		from
		moumou.business
		<where>
			<if test="id != null">
				and id= #{id,jdbcType=BIGINT}
			</if>
			<if test="userId != null">
				and user_id= #{userId,jdbcType=BIGINT}
			</if>
			<if test="businessName != null">
				and business_name= #{businessName,jdbcType=VARCHAR}
			</if>
			<if test="businessAddress != null">
				and business_address= #{businessAddress,jdbcType=VARCHAR}
			</if>
			<if test="businessTel != null">
				and business_tel= #{businessTel,jdbcType=VARCHAR}
			</if>
			<if test="businessSite != null">
				and business_site= #{businessSite,jdbcType=VARCHAR}
			</if>
			<if test="businessQq != null">
				and business_qq= #{businessQq,jdbcType=VARCHAR}
			</if>
			<if test="businessWeixin != null">
				and business_weixin= #{businessWeixin,jdbcType=VARCHAR}
			</if>
			<if test="businessWeibo != null">
				and business_weibo= #{businessWeibo,jdbcType=VARCHAR}
			</if>
			<if test="businessCredentialsUp != null">
				and business_credentials_up=
				#{businessCredentialsUp,jdbcType=VARCHAR}
			</if>
			<if test="businessCredentialsDown != null">
				and business_credentials_down=
				#{businessCredentialsDown,jdbcType=VARCHAR}
			</if>
			<if test="businessCredentialsFace != null">
				and business_credentials_face=
				#{businessCredentialsFace,jdbcType=VARCHAR}
			</if>
			<if test="createTime != null">
				and create_time= #{createTime,jdbcType=TIMESTAMP}
			</if>
			<if test="modfiyTime != null">
				and modfiy_time= #{modfiyTime,jdbcType=TIMESTAMP}
			</if>
			<if test="state != null">
				and state= #{state,jdbcType=TINYINT}
			</if>
			<if test="descb != null">
				and descb= #{descb,jdbcType=VARCHAR}
			</if>
			<if test="businessIndustry != null">
				and business_industry=
				#{businessIndustry,jdbcType=VARCHAR}
			</if>
			<if test="businessLogo != null">
				and business_logo= #{businessLogo,jdbcType=VARCHAR}
			</if>
			<if test="detailAddress != null">
				and detail_address= #{detailAddress,jdbcType=VARCHAR}
			</if>
			<if test="businessAbbreviation != null">
				and business_abbreviation=
				#{businessAbbreviation,jdbcType=VARCHAR},
			</if>
			<if test="registrationNumber != null">
				and registration_number=
				#{registrationNumber,jdbcType=VARCHAR},
			</if>
			<if test="applyName != null">
				and apply_name= #{applyName,jdbcType=VARCHAR},
			</if>
			<if test="identityCard != null">
				and identity_card= #{identityCard,jdbcType=VARCHAR},
			</if>
			<if test="certificationType != null">
				and certification_type=
				#{certificationType,jdbcType=INTEGER},
			</if>
		</where>
		<if test="order != null">
      <![CDATA[  order by  ${order} ]]>
		</if>
	</select>
	<select id="selectPageList" resultMap="BaseResultMap"
		parameterType="java.util.Map">
		select
		<include refid="Base_Column_List" />
		from
		moumou.business
		<where>
			<if test="id != null">
				and id= #{id,jdbcType=BIGINT}
			</if>
			<if test="userId != null">
				and user_id= #{userId,jdbcType=BIGINT}
			</if>
			<if test="businessName != null">
				and business_name= #{businessName,jdbcType=VARCHAR}
			</if>
			<if test="businessAddress != null">
				and business_address= #{businessAddress,jdbcType=VARCHAR}
			</if>
			<if test="businessTel != null">
				and business_tel= #{businessTel,jdbcType=VARCHAR}
			</if>
			<if test="businessSite != null">
				and business_site= #{businessSite,jdbcType=VARCHAR}
			</if>
			<if test="businessQq != null">
				and business_qq= #{businessQq,jdbcType=VARCHAR}
			</if>
			<if test="businessWeixin != null">
				and business_weixin= #{businessWeixin,jdbcType=VARCHAR}
			</if>
			<if test="businessWeibo != null">
				and business_weibo= #{businessWeibo,jdbcType=VARCHAR}
			</if>
			<if test="businessCredentialsUp != null">
				and business_credentials_up=
				#{businessCredentialsUp,jdbcType=VARCHAR}
			</if>
			<if test="businessCredentialsDown != null">
				and business_credentials_down=
				#{businessCredentialsDown,jdbcType=VARCHAR}
			</if>
			<if test="businessCredentialsFace != null">
				and business_credentials_face=
				#{businessCredentialsFace,jdbcType=VARCHAR}
			</if>
			<if test="createTimegt != null">
				and create_time >= #{createTimegt,jdbcType=TIMESTAMP}
			</if>
			<if test="createTimelt != null">
				and create_time <![CDATA[  <= ]]>
				#{createTimelt,jdbcType=TIMESTAMP}
			</if>
			<if test="createTime != null">
				and create_time= #{createTime,jdbcType=TIMESTAMP}
			</if>
			<if test="modfiyTime != null">
				and modfiy_time= #{modfiyTime,jdbcType=TIMESTAMP}
			</if>
			<if test="state != null">
				and state= #{state,jdbcType=TINYINT}
			</if>
			<if test="descb != null">
				and descb= #{descb,jdbcType=VARCHAR}
			</if>
			<if test="businessIndustry != null">
				and business_industry=
				#{businessIndustry,jdbcType=VARCHAR}
			</if>

			<if test="businessLogo != null">
				and business_logo= #{businessLogo,jdbcType=VARCHAR}
			</if>
			<if test="detailAddress != null">
				and detail_address= #{detailAddress,jdbcType=VARCHAR}
			</if>
			<if test="businessAbbreviation != null">
				and business_abbreviation=
				#{businessAbbreviation,jdbcType=VARCHAR},
			</if>
			<if test="registrationNumber != null">
				and registration_number=
				#{registrationNumber,jdbcType=VARCHAR},
			</if>
			<if test="applyName != null">
				and apply_name= #{applyName,jdbcType=VARCHAR},
			</if>
			<if test="identityCard != null">
				and identity_card= #{identityCard,jdbcType=VARCHAR},
			</if>
			<if test="certificationType != null">
				and certification_type=
				#{certificationType,jdbcType=INTEGER},
			</if>
		</where>
		<if test="order != null">
      <![CDATA[  order by  ${order} ]]>
		</if>
		<if test="page != null">
      <![CDATA[  limit #{page.begin}, #{page.end} ]]>
		</if>
	</select>
	<select id="selectCount" resultType="int" parameterType="java.util.Map">
		select
		count(1)
		from
		moumou.business
		<where>
			<if test="id != null">
				and id= #{id,jdbcType=BIGINT}
			</if>
			<if test="userId != null">
				and user_id= #{userId,jdbcType=BIGINT}
			</if>
			<if test="businessName != null">
				and business_name= #{businessName,jdbcType=VARCHAR}
			</if>
			<if test="businessAddress != null">
				and business_address= #{businessAddress,jdbcType=VARCHAR}
			</if>
			<if test="businessTel != null">
				and business_tel= #{businessTel,jdbcType=VARCHAR}
			</if>
			<if test="businessSite != null">
				and business_site= #{businessSite,jdbcType=VARCHAR}
			</if>
			<if test="businessQq != null">
				and business_qq= #{businessQq,jdbcType=VARCHAR}
			</if>
			<if test="businessWeixin != null">
				and business_weixin= #{businessWeixin,jdbcType=VARCHAR}
			</if>
			<if test="businessWeibo != null">
				and business_weibo= #{businessWeibo,jdbcType=VARCHAR}
			</if>
			<if test="businessCredentialsUp != null">
				and business_credentials_up=
				#{businessCredentialsUp,jdbcType=VARCHAR}
			</if>
			<if test="businessCredentialsDown != null">
				and business_credentials_down=
				#{businessCredentialsDown,jdbcType=VARCHAR}
			</if>
			<if test="businessCredentialsFace != null">
				and business_credentials_face=
				#{businessCredentialsFace,jdbcType=VARCHAR}
			</if>
			<if test="createTime != null">
				and create_time= #{createTime,jdbcType=TIMESTAMP}
			</if>
			<if test="modfiyTime != null">
				and modfiy_time= #{modfiyTime,jdbcType=TIMESTAMP}
			</if>
			<if test="state != null">
				and state= #{state,jdbcType=TINYINT}
			</if>
			<if test="descb != null">
				and descb= #{descb,jdbcType=VARCHAR}
			</if>
			<if test="businessIndustry != null">
				and business_industry=
				#{businessIndustry,jdbcType=VARCHAR}
			</if>
			<if test="businessLogo != null">
				and business_logo= #{businessLogo,jdbcType=VARCHAR}
			</if>
			<if test="detailAddress != null">
				and detail_address= #{detailAddress,jdbcType=VARCHAR}
			</if>
			<if test="businessAbbreviation != null">
				and business_abbreviation=
				#{businessAbbreviation,jdbcType=VARCHAR},
			</if>
			<if test="registrationNumber != null">
				and registration_number=
				#{registrationNumber,jdbcType=VARCHAR},
			</if>
			<if test="applyName != null">
				and apply_name= #{applyName,jdbcType=VARCHAR},
			</if>
			<if test="identityCard != null">
				and identity_card= #{identityCard,jdbcType=VARCHAR},
			</if>
			<if test="certificationType != null">
				and certification_type=
				#{certificationType,jdbcType=INTEGER},
			</if>
		</where>
	</select>
	<update id="updateByUserId" parameterType="com.mouchina.moumou_server.entity.member.Business">
		<!-- WARNING - @mbggenerated This element is automatically generated by 
			MyBatis Generator, do not modify. This element was generated on Mon Feb 01 
			16:24:57 CST 2016. -->
		update business
		<set>
			<if test="userId != null">
				user_id = #{userId,jdbcType=BIGINT},
			</if>
			<if test="businessName != null">
				business_name = #{businessName,jdbcType=VARCHAR},
			</if>
			<if test="businessAddress != null">
				business_address = #{businessAddress,jdbcType=VARCHAR},
			</if>
			<if test="businessTel != null">
				business_tel = #{businessTel,jdbcType=VARCHAR},
			</if>
			<if test="businessSite != null">
				business_site = #{businessSite,jdbcType=VARCHAR},
			</if>
			<if test="businessQq != null">
				business_qq = #{businessQq,jdbcType=VARCHAR},
			</if>
			<if test="businessWeixin != null">
				business_weixin = #{businessWeixin,jdbcType=VARCHAR},
			</if>
			<if test="businessWeibo != null">
				business_weibo = #{businessWeibo,jdbcType=VARCHAR},
			</if>
			<if test="businessCredentialsUp != null">
				business_credentials_up =
				#{businessCredentialsUp,jdbcType=VARCHAR},
			</if>
			<if test="businessCredentialsDown != null">
				business_credentials_down =
				#{businessCredentialsDown,jdbcType=VARCHAR},
			</if>
			<if test="businessCredentialsFace != null">
				business_credentials_face =
				#{businessCredentialsFace,jdbcType=VARCHAR},
			</if>
			<if test="createTime != null">
				create_time = #{createTime,jdbcType=TIMESTAMP},
			</if>
			<if test="modfiyTime != null">
				modfiy_time = #{modfiyTime,jdbcType=TIMESTAMP},
			</if>
			<if test="state != null">
				state = #{state,jdbcType=TINYINT},
			</if>
			<if test="descb != null">
				descb= #{descb,jdbcType=VARCHAR},
			</if>
			<if test="businessIndustry != null">
				business_industry= #{businessIndustry,jdbcType=VARCHAR},
			</if>
			<if test="businessLogo != null">
				business_logo= #{businessLogo,jdbcType=VARCHAR},
			</if>
			<if test="detailAddress != null">
				detail_address= #{detailAddress,jdbcType=VARCHAR},
			</if>
			<if test="businessAbbreviation != null">
				business_abbreviation=
				#{businessAbbreviation,jdbcType=VARCHAR},
			</if>
			<if test="registrationNumber != null">
				registration_number=
				#{registrationNumber,jdbcType=VARCHAR},
			</if>
			<if test="applyName != null">
				apply_name= #{applyName,jdbcType=VARCHAR},
			</if>
			<if test="identityCard != null">
				identity_card= #{identityCard,jdbcType=VARCHAR},
			</if>
			<if test="certificationType != null">
				certification_type=
				#{certificationType,jdbcType=INTEGER},
			</if>
			<if test="phone != null">
				phone=
				#{phone,jdbcType=CHAR},
			</if>
			
			<if test="province != null">
				province=
				#{province,jdbcType=VARCHAR},
			</if>
			<if test="city != null">
				city=
				#{city,jdbcType=VARCHAR},
			</if>
			<if test="area != null">
				area=
				#{area,jdbcType=VARCHAR},
			</if>
		</set>
		where user_id = #{userId,jdbcType=BIGINT}
	</update>
</mapper>